AUTHORS.txt
CHANGES.rst
LICENSE.txt
MANIFEST.in
README.rst
setup.py
django_mobile/__init__.py
django_mobile/conf.py
django_mobile/context_processors.py
django_mobile/loader.py
django_mobile/middleware.py
django_mobile/models.py
django_mobile/cache/__init__.py
django_mobile/cache/middleware.py
django_mobile_platform.egg-info/PKG-INFO
django_mobile_platform.egg-info/SOURCES.txt
django_mobile_platform.egg-info/dependency_links.txt
django_mobile_platform.egg-info/requires.txt
django_mobile_platform.egg-info/top_level.txt