Metadata-Version: 1.0
Name: django-mobile-platform
Version: 0.2.3
Summary: Detect mobile browsers and serve different template flavours to them.
Home-page: https://github.com/gregmuellegger/django-mobile
Author: Gregor Müllegger
Author-email: gregor@muellegger.de
License: BSD
Platform: UNKNOWN
Classifier: Development Status :: 4 - Beta
Classifier: Environment :: Web Environment
Classifier: Framework :: Django
Classifier: Intended Audience :: Developers
Classifier: License :: OSI Approved :: BSD License
Classifier: Natural Language :: English
Classifier: Operating System :: OS Independent
Classifier: Programming Language :: Python
